netbox_paloalto/__init__.py
netbox_paloalto/admin.py
netbox_paloalto/middleware.py
netbox_paloalto/models.py
netbox_paloalto/navigation.py
netbox_paloalto/signals.py
netbox_paloalto/template_content.py
netbox_paloalto/urls.py
netbox_paloalto/views.py
netbox_paloalto/migrations/0001_initial.py
netbox_paloalto/migrations/0002_auto_20200418_2232.py
netbox_paloalto/migrations/__init__.py
netbox_paloalto/templates/netbox_paloalto/error.html
netbox_paloalto/templates/netbox_paloalto/limitations.html
netbox_paloalto/templates/netbox_paloalto/rules.html
netbox_paloalto/templates/netbox_paloalto/search.html
netbox_paloalto-0.3.2.dist-info/LICENSE.txt
netbox_paloalto-0.3.2.dist-info/METADATA
netbox_paloalto-0.3.2.dist-info/WHEEL
netbox_paloalto-0.3.2.dist-info/top_level.txt
netbox_paloalto-0.3.2.dist-info/RECORD
