Metadata-Version: 2.1
Name: netbox-paloalto
Version: 0.3.2
Summary: List firewall rules from your Palo Alto firewall/Panorama using this NetBox plugin.
Home-page: https://github.com/rodvand/netbox-paloalto
Author: Martin Rødvand
Author-email: martin@rodvand.net
License: Apache 2.0
Platform: UNKNOWN
Classifier: Development Status :: 2 - Pre-Alpha
Classifier: Framework :: Django
Classifier: Framework :: Django :: 3.0
Classifier: License :: OSI Approved :: Apache Software License
Classifier: Programming Language :: Python :: 3
Classifier: Programming Language :: Python :: 3.6
Requires-Python: >=3.6
Requires-Dist: setuptools
Requires-Dist: pandevice
